fake_firestore/__init__.py
fake_firestore/_helpers.py
fake_firestore/_transformations.py
fake_firestore/client.py
fake_firestore/collection.py
fake_firestore/document.py
fake_firestore/exceptions.py
fake_firestore/query.py
fake_firestore/transaction.py
fake_firestore-0.3.0.dist-info/METADATA
fake_firestore-0.3.0.dist-info/WHEEL
fake_firestore-0.3.0.dist-info/licenses/LICENSE
fake_firestore-0.3.0.dist-info/RECORD
