Metadata-Version: 2.4
Name: fake-firestore
Version: 0.3.0
Summary: In-memory implementation of Google Cloud Firestore for use in tests
License: MIT
License-File: LICENSE
Keywords: firestore,gcp,testing,fake,pytest,asyncio
Author: Matt Dowds
Maintainer: Artem Kharchyshyn
Maintainer-email: xapart8@gmail.com
Requires-Python: >=3.8,<4.0
Classifier: License :: OSI Approved :: MIT License
Classifier: Programming Language :: Python :: 3
Classifier: Programming Language :: Python :: 3.8
Classifier: Programming Language :: Python :: 3.9
Classifier: Programming Language :: Python :: 3.10
Classifier: Programming Language :: Python :: 3.11
Classifier: Programming Language :: Python :: 3.12
Classifier: Programming Language :: Python :: 3.13
Classifier: Programming Language :: Python :: 3.14
Provides-Extra: async
Project-URL: Homepage, https://github.com/akharchyshyn/python-fake-firestore
Project-URL: Repository, https://github.com/akharchyshyn/python-fake-firestore
